{
"type": "FeatureCollection",
"name": "Perkins Outdoor Landmarks",
"crs": { "type": "name", "properties": { "name": "urn:ogc:def:crs:OGC:1.3:CRS84" } },
"features": [
{ "type": "Feature", "properties": { "Name": "Howe Bus Stop" }, "geometry": { "type": "Point", "coordinates": [ -71.1748590639545, 42.36153578733207, 58.222413532784202 ] } },
{ "type": "Feature", "properties": { "Name": "Perkins Health Center" }, "geometry": { "type": "Point", "coordinates": [ -71.17508202317451, 42.361669260288856, 58.222413532784202 ] } }
]
}
